.gitignore
CHANGES
LICENSE
README.rst
setup.cfg
setup.py
dalton/__init__.py
dalton.egg-info/PKG-INFO
dalton.egg-info/SOURCES.txt
dalton.egg-info/dependency_links.txt
dalton.egg-info/entry_points.txt
dalton.egg-info/not-zip-safe
dalton.egg-info/top_level.txt
dalton/tests/__init__.py
dalton/tests/test_files/step_0_response.txt
dalton/tests/test_files/test_output.txt
dalton/tests/test_recordings/__init__.py
dalton/tests/test_recordings/google_play_test/__init__.py
dalton/tests/test_recordings/google_play_test/step_0_response.txt
dalton/tests/test_recordings/google_test/__init__.py
google/__init__.py