Metadata-Version: 1.0
Name: dalton
Version: 1.0
Summary: An httplib injection library for recording and playing back HTTP interactions.
Home-page: https://github.com/bbangert/Dalton
Author: Ben Bangert
Author-email: ben@groovie.org
License: MIT
Keywords: mechanize httplib crawling mock test
Platform: UNKNOWN
Classifier: Development Status :: 5 - Production/Stable
Classifier: Intended Audience :: Developers
Classifier: License :: OSI Approved :: MIT License
Classifier: Topic :: Internet :: WWW/HTTP
Classifier: Topic :: Software Development :: Testing
